clinlp/__init__.py
clinlp/cli.py
clinlp/exceptions.py
clinlp/language.py
clinlp/normalizer.py
clinlp/sentencizer.py
clinlp/util.py
clinlp/ie/__init__.py
clinlp/ie/entity.py
clinlp/ie/term.py
clinlp/ie/qualifier/__init__.py
clinlp/ie/qualifier/context_algorithm.py
clinlp/ie/qualifier/qualifier.py
clinlp/ie/qualifier/transformer.py
clinlp/metrics/__init__.py
clinlp/metrics/ie.py
clinlp/resources/__init__.py
clinlp/resources/context_rules.json
clinlp-0.10.0.dist-info/licenses/LICENSE
clinlp_apps/ie_demo/README.md
clinlp_apps/ie_demo/app.py
clinlp_apps/ie_demo/resources/sample_terms.json
clinlp_apps/ie_demo/resources/sample_text.txt
clinlp_apps/ie_demo/src/__init__.py
clinlp_apps/ie_demo/src/controller.py
clinlp_apps/ie_demo/src/model.py
clinlp_apps/ie_demo/src/utils.py
clinlp_apps/ie_demo/src/view.py
clinlp-0.10.0.dist-info/METADATA
clinlp-0.10.0.dist-info/WHEEL
clinlp-0.10.0.dist-info/entry_points.txt
clinlp-0.10.0.dist-info/top_level.txt
clinlp-0.10.0.dist-info/RECORD
