Metadata-Version: 2.4
Name: clinlp
Version: 0.10.0
Summary: Performant and production-ready NLP pipelines for clinical text written in Dutch
Author-email: Vincent Menger <v.j.menger-2@umcutrecht.nl>, Bram van Es <b.vanes-3@umcutrecht.nl>
Project-URL: Documentation, https://clinlp.readthedocs.io/en/latest/
Project-URL: Repository, https://github.com/umcu/clinlp
Project-URL: Issues, https://github.com/umcu/clinlp/issues
Project-URL: Changelog, https://github.com/umcu/clinlp/blob/main/CHANGELOG.md
Classifier: Programming Language :: Python :: 3.11
Classifier: Programming Language :: Python :: 3.12
Classifier: Programming Language :: Python :: 3.13
Requires-Python: >=3.11
License-File: LICENSE
Requires-Dist: click~=8.3
Requires-Dist: intervaltree~=3.1
Requires-Dist: makefun~=1.16
Requires-Dist: numpy~=2.3
Requires-Dist: pandas~=2.3
Requires-Dist: pydantic~=2.11
Requires-Dist: spacy~=3.8
Provides-Extra: metrics
Requires-Dist: nervaluate==0.1.8; extra == "metrics"
Requires-Dist: scikit-learn~=1.7; extra == "metrics"
Provides-Extra: transformers
Requires-Dist: transformers[torch]~=4.56; extra == "transformers"
Provides-Extra: apps
Requires-Dist: dash-bootstrap-components~=2.0; extra == "apps"
Requires-Dist: dash~=3.2; extra == "apps"
Dynamic: license-file
